lambda_router/__init__.py
lambda_router/app.py
lambda_router/appsync.py
lambda_router/config.py
lambda_router/events.py
lambda_router/exceptions.py
lambda_router/interfaces.py
lambda_router/proxies.py
lambda_router/routers.py
lambda_router-2021.3.1.dist-info/LICENSE
lambda_router-2021.3.1.dist-info/METADATA
lambda_router-2021.3.1.dist-info/WHEEL
lambda_router-2021.3.1.dist-info/top_level.txt
lambda_router-2021.3.1.dist-info/RECORD
