Metadata-Version: 2.1
Name: lambda-router
Version: 2021.3.1
Summary: AWS Lambda Routing Utility
Home-page: https://github.com/jasureinc/lambda-router
Author: Jason Paidoussi
Author-email: jason@paidoussi.net
License: BSD 3 Clause
Platform: UNKNOWN
Classifier: Development Status :: 3 - Alpha
Classifier: Programming Language :: Python
Classifier: Programming Language :: Python :: 3
Classifier: Programming Language :: Python :: 3.7
Classifier: Programming Language :: Python :: 3.8
Classifier: License :: OSI Approved :: BSD License
Classifier: Topic :: Software Development :: Libraries :: Python Modules
Requires-Dist: attrs (>=20.3.0)
Requires-Dist: jsonpath-rw (>=1.4.0)
Provides-Extra: docs
Requires-Dist: sphinx ; extra == 'docs'
Provides-Extra: tests
Requires-Dist: coverage[toml] ; extra == 'tests'
Requires-Dist: pytest ; extra == 'tests'
